{"images/apple.png":["images/apple.png"],"images/google.png":["images/google.png"],"images/is.jpg":["images/is.jpg"],"images/logo.jpg":["images/logo.jpg"],"images/logo2.jpg":["images/logo2.jpg"],"images/man.png":["images/man.png"],"images/me.jpg":["images/me.jpg"],"images/short_logo2.jpg":["images/short_logo2.jpg"],"images/yapi.jpg":["images/yapi.jpg"],"images/ziraat.jpg":["images/ziraat.jpg"],"packages/cupertino_icons/assets/CupertinoIcons.ttf":["packages/cupertino_icons/assets/CupertinoIcons.ttf"]}